interceptoraptor/__init__.py
interceptoraptor/cli.py
interceptoraptor/decorator.py
interceptoraptor/generics.py
interceptoraptor/storage/__init__.py
interceptoraptor/storage/sqllite3.py
interceptoraptor-0.0.3.dist-info/METADATA
interceptoraptor-0.0.3.dist-info/WHEEL
interceptoraptor-0.0.3.dist-info/entry_points.txt
interceptoraptor-0.0.3.dist-info/top_level.txt
interceptoraptor-0.0.3.dist-info/RECORD
