Metadata-Version: 2.1
Name: interceptoraptor
Version: 0.0.3
Summary: Intercept banana environment data (a.k.a. another VCR.py)
License: MIT License
Classifier: Intended Audience :: Developers
Classifier: Operating System :: OS Independent
Classifier: Programming Language :: Python
Classifier: Programming Language :: Python :: 3
Classifier: Topic :: Software Development :: Debuggers
Classifier: Topic :: Software Development :: Quality Assurance
Classifier: Topic :: Software Development :: Testing
Provides-Extra: deploy_to_pip
Requires-Dist: twine ; extra == 'deploy_to_pip'
Requires-Dist: build ; extra == 'deploy_to_pip'
Provides-Extra: dev
Requires-Dist: pytest ; extra == 'dev'
Requires-Dist: pylint ; extra == 'dev'
Requires-Dist: coverage ; extra == 'dev'
Requires-Dist: flake8 ; extra == 'dev'
Requires-Dist: sphinx ; extra == 'dev'
